README.rst
setup.cfg
setup.py
gmane/__init__.py
gmane/agentStatistics.py
gmane/downloadMessages.py
gmane/evolutionTimelines.py
gmane/interactionNetwork.py
gmane/listDataStructures.py
gmane/loadMessages.py
gmane/networkDrawer.py
gmane/networkEvolution.py
gmane/networkMeasures.py
gmane/networkPartitioning.py
gmane/pca.py
gmane/tableHelpers.py
gmane/timeStatistics.py
gmane.egg-info/PKG-INFO
gmane.egg-info/SOURCES.txt
gmane.egg-info/dependency_links.txt
gmane.egg-info/top_level.txt