Metadata-Version: 1.1
Name: gmane
Version: 0.1.dev24
Summary: Utilities for the analysis of the GMANE email list database
Home-page: https://github.com/ttm/gmane
Author: Renato Fabbri
Author-email: listamacambira@googlegroups.com
License: Public Domain
Keywords: complexity networks human interaction physics data mining analysis
Platform: UNKNOWN
Classifier: Development Status :: 2 - Pre-Alpha
Classifier: Intended Audience :: Science/Research
Classifier: Intended Audience :: Developers
Classifier: Intended Audience :: Information Technology
Classifier: Intended Audience :: Other Audience
Classifier: Topic :: Scientific/Engineering :: Physics
Classifier: Topic :: Scientific/Engineering :: Visualization
Classifier: Topic :: Scientific/Engineering :: Information Analysis
Classifier: Topic :: Communications :: Email
Classifier: Topic :: Text Processing
Classifier: Topic :: Text Processing :: Linguistic
Classifier: Topic :: Multimedia :: Graphics :: Presentation
Classifier: Topic :: Multimedia :: Sound/Audio :: Sound Synthesis
Classifier: Topic :: Multimedia :: Video :: Display
Classifier: Topic :: Artistic Software
Classifier: Topic :: Other/Nonlisted Topic
Classifier: License :: Public Domain
Classifier: Programming Language :: Python :: 3
